{
  "project_info": {
    "project_number": "615950408529",
    "project_id": "car-wash-app-86a16",
    "storage_bucket": "car-wash-app-86a16.appspot.com"
  },
  "client": [
    {
      "client_info": {
        "mobilesdk_app_id": "1:615950408529:android:1c6b4ac60e99263975d170",
        "android_client_info": {
          "package_name": "com.example.car_wash_app"
        }
      },
      "oauth_client": [],
      "api_key": [
        {
          "current_key": "AIzaSyAPPhEMNXvyATQu7lCHX_Xu6a6eik0XtmM"
        }
      ],
      "services": {
        "appinvite_service": {
          "other_platform_oauth_client": []
        }
      }
    }
  ],
  "configuration_version": "1"
}